{
  "posts": [
    {
      "id": 1,
      "title": "Fashion ala IU",
      "body": "Kenakan baju jadul sambil panas-panasan, pesonanya sukses bikin netter silau"
    },
    {
      "id": 2,
      "title": "Cherry Bullet",
      "body": "Cherry Bullet tertahan di Filipina akibat meletusnya gunung taal"
    },
    {
      "id": 3,
      "title": "Chen EXO",
      "body": "Berani jujur meski mendadak, penggemar EXO justru dukung keputusan Chen"
    }
    ],
  "profile": {
    "name": "nandoaditya"
  }
}
